hyperpocket_langgraph/__init__.py
hyperpocket_langgraph/pocket_langgraph.py
hyperpocket_langgraph-0.5.7.dist-info/METADATA
hyperpocket_langgraph-0.5.7.dist-info/WHEEL
hyperpocket_langgraph-0.5.7.dist-info/RECORD
